Metadata-Version: 2.1
Name: tla
Version: 0.0.2
Summary: Parser and syntax tree for TLA+, the temporal logic of actions.
Home-page: https://github.com/johnyf/tla
Author: Ioannis Filippidis
Author-email: jfilippidis@gmail.com
License: BSD
Keywords: TLA+,TLA,temporal logic of actions,formal,specification,expression,formula,module,mathematics,theorem,proof,parser,lexer,parsing,ast,abstract syntax tree,syntax tree
Classifier: Development Status :: 2 - Pre-Alpha
Classifier: Intended Audience :: Developers
Classifier: Intended Audience :: Science/Research
Classifier: License :: OSI Approved :: BSD License
Classifier: Operating System :: OS Independent
Classifier: Programming Language :: Python
Classifier: Programming Language :: Python :: 3 :: Only
Classifier: Topic :: Scientific/Engineering
Classifier: Topic :: Software Development :: Compilers
Requires-Python: >=3.10
License-File: LICENSE
Requires-Dist: parstools>=0.0.3
